<?xml version="1.0" encoding="UTF-8" standalone="no"?>
<lqn-model name="FutureModel">
  <solver-params comment=""/>
  <processor name="Meshify5800X570">
        
    <task multiplicity="1" name="kurz.ma.examples.simple.Main">
            
      <entry name="BES-kurz.ma.examples.simple.Main.public static main(java.lang.String[]):void">
                
        <entry-phase-activities>
                    
          <activity host-demand-mean="1.0002215285714285E9" name="public static main(java.lang.String[]):void" phase="1"/>
                  
        </entry-phase-activities>
              
      </entry>
          
    </task>
      
  </processor>
  <processor name="'Entry'-SimpleExample-0">
        
    <task name="SimpleExample-0_job_class_">
            
      <entry name="BES-'Entry'.'Entry'():&lt;&gt;" open-arrival-rate="0.00000000072530517967">
                
        <entry-phase-activities>
                    
          <activity host-demand-mean="1.0" name="public static main(java.lang.String[]):void" phase="1">
                        
            <synch-call calls-mean="1" dest="BES-kurz.ma.examples.simple.Main.public static main(java.lang.String[]):void"/>
                      
          </activity>
                  
        </entry-phase-activities>
              
      </entry>
          
    </task>
      
  </processor>
</lqn-model>
